desktop_env/__init__.py
desktop_env/actions.py
desktop_env/desktop_env.py
desktop_env/controllers/__init__.py
desktop_env/controllers/python.py
desktop_env/controllers/setup.py
desktop_env/evaluators/__init__.py
desktop_env/evaluators/getters/__init__.py
desktop_env/evaluators/getters/calc.py
desktop_env/evaluators/getters/chrome.py
desktop_env/evaluators/getters/file.py
desktop_env/evaluators/getters/general.py
desktop_env/evaluators/getters/gimp.py
desktop_env/evaluators/getters/impress.py
desktop_env/evaluators/getters/info.py
desktop_env/evaluators/getters/misc.py
desktop_env/evaluators/getters/replay.py
desktop_env/evaluators/getters/vlc.py
desktop_env/evaluators/getters/vscode.py
desktop_env/evaluators/metrics/__init__.py
desktop_env/evaluators/metrics/basic_os.py
desktop_env/evaluators/metrics/chrome.py
desktop_env/evaluators/metrics/docs.py
desktop_env/evaluators/metrics/general.py
desktop_env/evaluators/metrics/gimp.py
desktop_env/evaluators/metrics/libreoffice.py
desktop_env/evaluators/metrics/others.py
desktop_env/evaluators/metrics/pdf.py
desktop_env/evaluators/metrics/slides.py
desktop_env/evaluators/metrics/table.py
desktop_env/evaluators/metrics/thunderbird.py
desktop_env/evaluators/metrics/utils.py
desktop_env/evaluators/metrics/vlc.py
desktop_env/evaluators/metrics/vscode.py
desktop_env/providers/__init__.py
desktop_env/providers/base.py
desktop_env/providers/aws/__init__.py
desktop_env/providers/aws/manager.py
desktop_env/providers/aws/provider.py
desktop_env/providers/aws/provider_with_proxy.py
desktop_env/providers/aws/proxy_pool.py
desktop_env/providers/azure/__init__.py
desktop_env/providers/azure/manager.py
desktop_env/providers/azure/provider.py
desktop_env/providers/gcp/__init__.py
desktop_env/providers/gcp/manager.py
desktop_env/providers/gcp/provider.py
desktop_env/providers/virtualbox/__init__.py
desktop_env/providers/virtualbox/manager.py
desktop_env/providers/virtualbox/provider.py
desktop_env/providers/vmware/__init__.py
lybic_guiagents-0.8.2.dist-info/licenses/LICENSE
lybic_guiagents-0.8.2.dist-info/METADATA
lybic_guiagents-0.8.2.dist-info/WHEEL
lybic_guiagents-0.8.2.dist-info/entry_points.txt
lybic_guiagents-0.8.2.dist-info/top_level.txt
lybic_guiagents-0.8.2.dist-info/RECORD
