Metadata-Version: 2.4
Name: lybic-guiagents
Version: 0.8.2
Summary: An open-source agentic framework that enables AI to use computers like humans and can provide a multi-agent runtime environment as an infrastructure capability
Author: Lybic Development Team
Author-email: Lybic Development Team <lybic@tingyutech.com>
License-Expression: Apache-2.0
Classifier: Programming Language :: Python :: 3
Requires-Python: >=3.12, <3.15
License-File: LICENSE
Requires-Dist: dotenv
Requires-Dist: pyperclip
Requires-Dist: Pillow>=11.3.0
Requires-Dist: backoff
Requires-Dist: numpy
Requires-Dist: anthropic
Requires-Dist: openai
Requires-Dist: google-genai
Requires-Dist: zhipuai>=2.1.5.20250106
Requires-Dist: groq
Requires-Dist: boto3
Requires-Dist: scikit-learn
Requires-Dist: tiktoken
Requires-Dist: lybic<1.0.0,>=0.12.0
Requires-Dist: pyobjc; platform_system == "Darwin"
Requires-Dist: oa_atomacos; platform_system == "Darwin"
Requires-Dist: pywinauto; platform_system == "Windows"
Requires-Dist: pywin32; platform_system == "Windows"
Requires-Dist: pytest>=8.4.2
Requires-Dist: protobuf>=5.29.5
Requires-Dist: googleapis-common-protos>=1.70.0
Requires-Dist: filelock
Provides-Extra: postgres
Requires-Dist: asyncpg>=0.29.0; extra == "postgres"
Provides-Extra: dev
Requires-Dist: pytest; extra == "dev"
Requires-Dist: anyio; extra == "dev"
Requires-Dist: pytest-asyncio; extra == "dev"
Requires-Dist: pytest-tornasync; extra == "dev"
Requires-Dist: pytest-trio; extra == "dev"
Requires-Dist: pytest-twisted; extra == "dev"
Requires-Dist: twisted; extra == "dev"
Provides-Extra: grpc
Requires-Dist: grpcio; extra == "grpc"
Requires-Dist: grpcio-tools>=1.71.2; extra == "grpc"
Provides-Extra: prometheus
Requires-Dist: prometheus-client>=0.20.0; extra == "prometheus"
Requires-Dist: psutil>=5.9.0; extra == "prometheus"
Provides-Extra: mcp
Requires-Dist: mcp>=1.0.0; extra == "mcp"
Requires-Dist: fastapi>=0.122.0; extra == "mcp"
Requires-Dist: sse-starlette>=2.0.0; extra == "mcp"
Requires-Dist: uvicorn>=0.30.0; extra == "mcp"
Provides-Extra: restful
Requires-Dist: fastapi>=0.122.0; extra == "restful"
Requires-Dist: sse-starlette>=2.0.0; extra == "restful"
Requires-Dist: uvicorn>=0.30.0; extra == "restful"
Provides-Extra: vmware-and-evaluation
Requires-Dist: python-pptx; extra == "vmware-and-evaluation"
Requires-Dist: odfpy; extra == "vmware-and-evaluation"
Requires-Dist: openpyxl; extra == "vmware-and-evaluation"
Requires-Dist: pandas; extra == "vmware-and-evaluation"
Requires-Dist: lxml; extra == "vmware-and-evaluation"
Requires-Dist: xmltodict; extra == "vmware-and-evaluation"
Requires-Dist: opencv-python-headless; extra == "vmware-and-evaluation"
Requires-Dist: rapidfuzz; extra == "vmware-and-evaluation"
Requires-Dist: imagehash; extra == "vmware-and-evaluation"
Requires-Dist: odfpy; extra == "vmware-and-evaluation"
Requires-Dist: pdfplumber; extra == "vmware-and-evaluation"
Requires-Dist: PyYAML; extra == "vmware-and-evaluation"
Requires-Dist: mutagen; extra == "vmware-and-evaluation"
Requires-Dist: pypdf; extra == "vmware-and-evaluation"
Requires-Dist: PyMuPDF; extra == "vmware-and-evaluation"
Requires-Dist: formulas; extra == "vmware-and-evaluation"
Requires-Dist: pyacoustid; extra == "vmware-and-evaluation"
Requires-Dist: opencv-python~=4.8.1.78; extra == "vmware-and-evaluation"
Requires-Dist: PyPDF2; extra == "vmware-and-evaluation"
Requires-Dist: librosa; extra == "vmware-and-evaluation"
Requires-Dist: fastdtw; extra == "vmware-and-evaluation"
Requires-Dist: scikit-learn; extra == "vmware-and-evaluation"
Requires-Dist: scikit-image; extra == "vmware-and-evaluation"
Requires-Dist: bs4; extra == "vmware-and-evaluation"
Requires-Dist: azure-identity; extra == "vmware-and-evaluation"
Requires-Dist: azure-mgmt-compute; extra == "vmware-and-evaluation"
Requires-Dist: azure-mgmt-network; extra == "vmware-and-evaluation"
Requires-Dist: toml; extra == "vmware-and-evaluation"
Requires-Dist: easyocr; extra == "vmware-and-evaluation"
Provides-Extra: pyautogui
Requires-Dist: pyautogui; extra == "pyautogui"
Provides-Extra: all
Requires-Dist: toml; extra == "all"
Requires-Dist: numpy; extra == "all"
Requires-Dist: backoff; extra == "all"
Requires-Dist: pandas; extra == "all"
Requires-Dist: openai; extra == "all"
Requires-Dist: anthropic; extra == "all"
Requires-Dist: zhipuai; extra == "all"
Requires-Dist: groq; extra == "all"
Requires-Dist: boto3; extra == "all"
Requires-Dist: paddlepaddle; extra == "all"
Requires-Dist: tiktoken; extra == "all"
Requires-Dist: toml; extra == "all"
Requires-Dist: exa_py; extra == "all"
Requires-Dist: google-genai; extra == "all"
Requires-Dist: python-dotenv; extra == "all"
Requires-Dist: Pillow>=11.3.0; extra == "all"
Requires-Dist: gymnasium~=0.28.1; extra == "all"
Requires-Dist: requests<2.33,>=2.31; extra == "all"
Requires-Dist: pytz~=2024.1; extra == "all"
Requires-Dist: psutil<7.2.0,>=5.9.6; extra == "all"
Requires-Dist: tqdm~=4.65.0; extra == "all"
Requires-Dist: flask~=3.0.0; extra == "all"
Requires-Dist: requests-toolbelt~=1.0.0; extra == "all"
Requires-Dist: lxml; extra == "all"
Requires-Dist: xmltodict; extra == "all"
Requires-Dist: PyGetWindow; extra == "all"
Requires-Dist: ImageHash; extra == "all"
Requires-Dist: scikit-image; extra == "all"
Requires-Dist: formulas; extra == "all"
Requires-Dist: pydrive; extra == "all"
Requires-Dist: fastdtw; extra == "all"
Requires-Dist: odfpy; extra == "all"
Requires-Dist: func-timeout; extra == "all"
Requires-Dist: beautifulsoup4; extra == "all"
Requires-Dist: dashscope; extra == "all"
Requires-Dist: google-generativeai; extra == "all"
Requires-Dist: PyYaml; extra == "all"
Requires-Dist: mutagen; extra == "all"
Requires-Dist: easyocr; extra == "all"
Requires-Dist: borb; extra == "all"
Requires-Dist: pypdf2; extra == "all"
Requires-Dist: lybic>=0.7.3; extra == "all"
Requires-Dist: pdfplumber; extra == "all"
Requires-Dist: azure-identity; extra == "all"
Requires-Dist: azure-mgmt-compute; extra == "all"
Requires-Dist: azure-mgmt-network; extra == "all"
Requires-Dist: docker; extra == "all"
Requires-Dist: dotenv; extra == "all"
Requires-Dist: python-pptx; extra == "all"
Requires-Dist: odfpy; extra == "all"
Requires-Dist: openpyxl; extra == "all"
Requires-Dist: pandas; extra == "all"
Requires-Dist: lxml; extra == "all"
Requires-Dist: xmltodict; extra == "all"
Requires-Dist: opencv-python-headless; extra == "all"
Requires-Dist: Pillow; extra == "all"
Requires-Dist: imagehash; extra == "all"
Requires-Dist: rapidfuzz; extra == "all"
Requires-Dist: fitz; extra == "all"
Requires-Dist: imagehash; extra == "all"
Requires-Dist: odfpy; extra == "all"
Requires-Dist: pdfplumber; extra == "all"
Requires-Dist: PyYaml; extra == "all"
Requires-Dist: mutagen; extra == "all"
Requires-Dist: pypdf; extra == "all"
Requires-Dist: PyMuPDF; extra == "all"
Requires-Dist: formulas; extra == "all"
Requires-Dist: pyacoustid; extra == "all"
Requires-Dist: opencv-python~=4.8.1.78; extra == "all"
Requires-Dist: PyPDF2; extra == "all"
Requires-Dist: librosa; extra == "all"
Requires-Dist: fastdtw; extra == "all"
Requires-Dist: scikit-learn; extra == "all"
Requires-Dist: scikit-image; extra == "all"
Requires-Dist: bs4; extra == "all"
Requires-Dist: azure-identity; extra == "all"
Requires-Dist: azure-mgmt-compute; extra == "all"
Requires-Dist: azure-mgmt-network; extra == "all"
Requires-Dist: easyocr; extra == "all"
Requires-Dist: pyobjc; platform_system == "Darwin" and extra == "all"
Requires-Dist: oa_atomacos; platform_system == "Darwin" and extra == "all"
Requires-Dist: pywinauto; platform_system == "Windows" and extra == "all"
Requires-Dist: pywin32; platform_system == "Windows" and extra == "all"
Requires-Dist: grpcio; extra == "all"
Requires-Dist: grpcio-tools>=1.71.2; extra == "all"
Dynamic: author
Dynamic: license-file
Dynamic: requires-python
